jvc_pyjector/__init__.py
jvc_pyjector/constants.py
jvc_pyjector-0.0.1.dist-info/LICENSE
jvc_pyjector-0.0.1.dist-info/METADATA
jvc_pyjector-0.0.1.dist-info/WHEEL
jvc_pyjector-0.0.1.dist-info/top_level.txt
jvc_pyjector-0.0.1.dist-info/RECORD
