Metadata-Version: 2.1
Name: jvc-pyjector
Version: 0.0.1
Summary: Basic python library to interface with JVC Projectors
Home-page: https://github.com/nralego8/jvc_pyjector
Author: nralego8
License: UNKNOWN
Platform: UNKNOWN
Classifier: Programming Language :: Python :: 3
Classifier: License :: OSI Approved :: GNU General Public License v3 (GPLv3)
Classifier: Operating System :: OS Independent
Requires-Python: >=3.6
License-File: LICENSE
